Workbook
Name Slicer_City1: #N/A

Sheet Products
A1: Product_ID | B1: Product_Name | C1: Category | D1: COGS | E1: Selling Price | F1: Gross_Margin_%
A2: P001 | B2: Lotus Stud Earrings | C2: Earrings | D2: 80 | E2: 220 | F2: 0.64
A3: P002 | B3: Kundan Choker | C3: Necklace | D3: 180 | E3: 450 | F3: 0.6
A4: P003 | B4: Oxidised Bangle Set | C4: Bangles | D4: 120 | E4: 300 | F4: 0.6
A5: P004 | B5: Pearl Drop Earrings | C5: =C2 -> Earrings | D5: 90 | E5: 250 | F5: =F2 -> 0.64
A6: P005 | B6: Terracotta Necklace | C6: =C3 -> Necklace | D6: 100 | E6: 280 | F6: =F5 -> 0.64
A7: P006 | B7: Ghungroo Anklet | C7: Anklets | D7: 60 | E7: 180 | F7: 0.67
A8: P007 | B8: Mirror Work Earrings | C8: =C2 -> Earrings | D8: 70 | E8: 200 | F8: 0.65
A9: P008 | B9: Silver Toe Ring Set | C9: Toe Rings | D9: 40 | E9: 120 | F9: 0.67

Sheet Custromers
A1: Column1 | B1: Column2 | C1: Column3 | D1: Column4
A2: Customer_ID | B2: Customer_Name | C2: City | D2: Customer_Type
A3: C001 | B3: Priya Sharma | C3: Delhi | D3: Repeat
A4: C002 | B4: Ananya Bose | C4: Kolkata | D4: New
A5: C003 | B5: Meera Iyer | C5: Bangalore | D5: Repeat
A6: C004 | B6: Ritu Agarwal | C6: Jaipur | D6: New
A7: C005 | B7: Sneha Pillai | C7: Mumbai | D7: Repeat
A8: C006 | B8: Divya Nair | C8: =C5 -> Bangalore | D8: New
A9: C007 | B9: Kavita Mishra | C9: =C3 -> Delhi | D9: Repeat
A10: C008 | B10: Pooja Reddy | C10: Hyderabad | D10: New
A11: C009 | B11: Nisha Gupta | C11: =C6 -> Jaipur | D11: Repeat
A12: C010 | B12: Tanvi Mehta | C12: =C3 -> Delhi | D12: New

Sheet Orders
A1: Order_ID | B1: Order_Date | C1: Customer_ID | D1: Product_ID | E1: Quantity | F1: Order_Month | G1: Product_Name | H1: Selling_Price | I1: COGS | J1: Revenue | K1: Gross_Profit | L1: City | M1: Category
A2: ORD001 | B2: 45383 | C2: C001 | D2: P002 | E2: 1 | F2: 45383 | G2: =INDEX(Products!B:B,MATCH(D2,Products!A:A,0)) -> Kundan Choker | H2: =INDEX(Products!E:E,MATCH(D2,Products!A:A,0)) -> 450 | I2: =INDEX(Products!D:D,MATCH(D2,Products!A:A,0)) -> 180 | J2: =H2*E2 -> 450 | K2: =(H2-I2)*E2 -> 270 | L2: =INDEX(Custromers!C:C,MATCH(Orders!C2,Custromers!A:A,0)) -> Delhi | M2: =INDEX(Products!C:C,MATCH(Orders!D2,Products!A:A,0)) -> Necklace
A3: ORD002 | B3: 45387 | C3: C003 | D3: P001 | E3: 2 | F3: 45383 | G3: =INDEX(Products!B:B,MATCH(D3,Products!A:A,0)) -> Lotus Stud Earrings | H3: =INDEX(Products!E:E,MATCH(D3,Products!A:A,0)) -> 220 | I3: =INDEX(Products!D:D,MATCH(D3,Products!A:A,0)) -> 80 | J3: =H3*E3 -> 440 | K3: =(H3-I3)*E3 -> 280 | L3: =INDEX(Custromers!C:C,MATCH(Orders!C3,Custromers!A:A,0)) -> Bangalore | M3: =INDEX(Products!C:C,MATCH(Orders!D3,Products!A:A,0)) -> Earrings
A4: ORD003 | B4: 45392 | C4: C005 | D4: P006 | E4: 1 | F4: 45383 | G4: =INDEX(Products!B:B,MATCH(D4,Products!A:A,0)) -> Ghungroo Anklet | H4: =INDEX(Products!E:E,MATCH(D4,Products!A:A,0)) -> 180 | I4: =INDEX(Products!D:D,MATCH(D4,Products!A:A,0)) -> 60 | J4: =H4*E4 -> 180 | K4: =(H4-I4)*E4 -> 120 | L4: =INDEX(Custromers!C:C,MATCH(Orders!C4,Custromers!A:A,0)) -> Mumbai | M4: =INDEX(Products!C:C,MATCH(Orders!D4,Products!A:A,0)) -> Anklets
A5: ORD004 | B5: 45400 | C5: C002 | D5: P004 | E5: 1 | F5: 45383 | G5: =INDEX(Products!B:B,MATCH(D5,Products!A:A,0)) -> Pearl Drop Earrings | H5: =INDEX(Products!E:E,MATCH(D5,Products!A:A,0)) -> 250 | I5: =INDEX(Products!D:D,MATCH(D5,Products!A:A,0)) -> 90 | J5: =H5*E5 -> 250 | K5: =(H5-I5)*E5 -> 160 | L5: =INDEX(Custromers!C:C,MATCH(Orders!C5,Custromers!A:A,0)) -> Kolkata | M5: =INDEX(Products!C:C,MATCH(Orders!D5,Products!A:A,0)) -> Earrings
A6: ORD005 | B6: 45407 | C6: C007 | D6: P003 | E6: 1 | F6: 45383 | G6: =INDEX(Products!B:B,MATCH(D6,Products!A:A,0)) -> Oxidised Bangle Set | H6: =INDEX(Products!E:E,MATCH(D6,Products!A:A,0)) -> 300 | I6: =INDEX(Products!D:D,MATCH(D6,Products!A:A,0)) -> 120 | J6: =H6*E6 -> 300 | K6: =(H6-I6)*E6 -> 180 | L6: =INDEX(Custromers!C:C,MATCH(Orders!C6,Custromers!A:A,0)) -> Delhi | M6: =INDEX(Products!C:C,MATCH(Orders!D6,Products!A:A,0)) -> Bangles
A7: ORD006 | B7: 45414 | C7: C004 | D7: P007 | E7: 2 | F7: 45413 | G7: =INDEX(Products!B:B,MATCH(D7,Products!A:A,0)) -> Mirror Work Earrings | H7: =INDEX(Products!E:E,MATCH(D7,Products!A:A,0)) -> 200 | I7: =INDEX(Products!D:D,MATCH(D7,Products!A:A,0)) -> 70 | J7: =H7*E7 -> 400 | K7: =(H7-I7)*E7 -> 260 | L7: =INDEX(Custromers!C:C,MATCH(Orders!C7,Custromers!A:A,0)) -> Jaipur | M7: =INDEX(Products!C:C,MATCH(Orders!D7,Products!A:A,0)) -> Earrings
A8: ORD007 | B8: 45420 | C8: C008 | D8: P005 | E8: 1 | F8: 45413 | G8: =INDEX(Products!B:B,MATCH(D8,Products!A:A,0)) -> Terracotta Necklace | H8: =INDEX(Products!E:E,MATCH(D8,Products!A:A,0)) -> 280 | I8: =INDEX(Products!D:D,MATCH(D8,Products!A:A,0)) -> 100 | J8: =H8*E8 -> 280 | K8: =(H8-I8)*E8 -> 180 | L8: =INDEX(Custromers!C:C,MATCH(Orders!C8,Custromers!A:A,0)) -> Hyderabad | M8: =INDEX(Products!C:C,MATCH(Orders!D8,Products!A:A,0)) -> Necklace
A9: ORD008 | B9: 45427 | C9: C001 | D9: P002 | E9: 1 | F9: 45413 | G9: =INDEX(Products!B:B,MATCH(D9,Products!A:A,0)) -> Kundan Choker | H9: =INDEX(Products!E:E,MATCH(D9,Products!A:A,0)) -> 450 | I9: =INDEX(Products!D:D,MATCH(D9,Products!A:A,0)) -> 180 | J9: =H9*E9 -> 450 | K9: =(H9-I9)*E9 -> 270 | L9: =INDEX(Custromers!C:C,MATCH(Orders!C9,Custromers!A:A,0)) -> Delhi | M9: =INDEX(Products!C:C,MATCH(Orders!D9,Products!A:A,0)) -> Necklace
A10: ORD009 | B10: 45434 | C10: C006 | D10: P001 | E10: 3 | F10: 45413 | G10: =INDEX(Products!B:B,MATCH(D10,Products!A:A,0)) -> Lotus Stud Earrings | H10: =INDEX(Products!E:E,MATCH(D10,Products!A:A,0)) -> 220 | I10: =INDEX(Products!D:D,MATCH(D10,Products!A:A,0)) -> 80 | J10: =H10*E10 -> 660 | K10: =(H10-I10)*E10 -> 420 | L10: =INDEX(Custromers!C:C,MATCH(Orders!C10,Custromers!A:A,0)) -> Bangalore | M10: =INDEX(Products!C:C,MATCH(Orders!D10,Products!A:A,0)) -> Earrings
A11: ORD010 | B11: 45440 | C11: C010 | D11: P008 | E11: 2 | F11: 45413 | G11: =INDEX(Products!B:B,MATCH(D11,Products!A:A,0)) -> Silver Toe Ring Set | H11: =INDEX(Products!E:E,MATCH(D11,Products!A:A,0)) -> 120 | I11: =INDEX(Products!D:D,MATCH(D11,Products!A:A,0)) -> 40 | J11: =H11*E11 -> 240 | K11: =(H11-I11)*E11 -> 160 | L11: =INDEX(Custromers!C:C,MATCH(Orders!C11,Custromers!A:A,0)) -> Delhi | M11: =INDEX(Products!C:C,MATCH(Orders!D11,Products!A:A,0)) -> Toe Rings
A12: ORD011 | B12: 45446 | C12: C003 | D12: P003 | E12: 1 | F12: 45444 | G12: =INDEX(Products!B:B,MATCH(D12,Products!A:A,0)) -> Oxidised Bangle Set | H12: =INDEX(Products!E:E,MATCH(D12,Products!A:A,0)) -> 300 | I12: =INDEX(Products!D:D,MATCH(D12,Products!A:A,0)) -> 120 | J12: =H12*E12 -> 300 | K12: =(H12-I12)*E12 -> 180 | L12: =INDEX(Custromers!C:C,MATCH(Orders!C12,Custromers!A:A,0)) -> Bangalore | M12: =INDEX(Products!C:C,MATCH(Orders!D12,Products!A:A,0)) -> Bangles
A13: ORD012 | B13: 45452 | C13: C009 | D13: P006 | E13: 2 | F13: 45444 | G13: =INDEX(Products!B:B,MATCH(D13,Products!A:A,0)) -> Ghungroo Anklet | H13: =INDEX(Products!E:E,MATCH(D13,Products!A:A,0)) -> 180 | I13: =INDEX(Products!D:D,MATCH(D13,Products!A:A,0)) -> 60 | J13: =H13*E13 -> 360 | K13: =(H13-I13)*E13 -> 240 | L13: =INDEX(Custromers!C:C,MATCH(Orders!C13,Custromers!A:A,0)) -> Jaipur | M13: =INDEX(Products!C:C,MATCH(Orders!D13,Products!A:A,0)) -> Anklets
... A26: ORD025 | B26: 45533 | C26: C007 | D26: P003 | E26: 2 | F26: 45505 | G26: =INDEX(Products!B:B,MATCH(D26,Products!A:A,0)) -> Oxidised Bangle Set | H26: =INDEX(Products!E:E,MATCH(D26,Products!A:A,0)) -> 300 | I26: =INDEX(Products!D:D,MATCH(D26,Products!A:A,0)) -> 120 | J26: =H26*E26 -> 600 | K26: =(H26-I26)*E26 -> 360 | L26: =INDEX(Custromers!C:C,MATCH(Orders!C26,Custromers!A:A,0)) -> Delhi | M26: =INDEX(Products!C:C,MATCH(Orders!D26,Products!A:A,0)) -> Bangles

Sheet Pivot_month
A3: Row Labels | B3: Sum of Revenue
A4: 45383 | B4: 1620
A5: 45413 | B5: 2030
A6: 45444 | B6: 1670
A7: 45474 | B7: 1980
A8: 45505 | B8: 2210
A9: Grand Total | B9: 9510

Sheet Pivot_product
A3: Row Labels | B3: Sum of Revenue | C3: Sum of Gross_Profit
A4: Ghungroo Anklet | B4: 1080 | C4: 720
A5: Kundan Choker | B5: 1800 | C5: 1080
A6: Lotus Stud Earrings | B6: 1540 | C6: 980
A7: Mirror Work Earrings | B7: 1000 | C7: 650
A8: Oxidised Bangle Set | B8: 1500 | C8: 900
A9: Pearl Drop Earrings | B9: 750 | C9: 480
A10: Silver Toe Ring Set | B10: 720 | C10: 480
A11: Terracotta Necklace | B11: 1120 | C11: 720
A12: Grand Total | B12: 9510 | C12: 6010

Sheet Pivot_category
A3: Row Labels | B3: Sum of Revenue
A4: Anklets | B4: 1080
A5: Bangles | B5: 1500
A6: Earrings | B6: 3290
A7: Necklace | B7: 2920
A8: Toe Rings | B8: 720
A9: Grand Total | B9: 9510

Sheet Pivot_city
A3: Row Labels | B3: Sum of Revenue
A4: Bangalore | B4: 2050
A5: Delhi | B5: 4060
A6: Hyderabad | B6: 580
A7: Jaipur | B7: 1490
A8: Kolkata | B8: 450
A9: Mumbai | B9: 880
A10: Grand Total | B10: 9510

Sheet Dashboard
B2: Business Performance Dashboard
B3: Period: April 2026 – August 20246| D2C Handcrafted Jewellery
B7: Total Revenue | C7: =SUM(Orders!J:J) -> 9510
B8: Total Orders | C8: =COUNTA(Orders!A:A)-1 -> 25
B9: Average Order Value | C9: =C7/C8 -> 380.4
B10: Total Gross Profit | C10: =SUM(Orders!K:K) -> 6010
B11: Gross Margin % | C11: =C10/C7 -> 0.63196635
B12: Avg. Revenue per Customer (LTV proxy) | C12: =C7/C13 -> 951
B13: Unique Customers | C13: =SUMPRODUCT(1/COUNTIF(Orders!C2:C26,Orders!C2:C26)) -> 10
B14: CAC | C14: Data not available
B52: Built by Sanskriti | BCom Hons, IPCW | Elara D2C Brand
